{
  "stream": {
    "count": 121,
    "rules": {
      "player_button": "button.episodes-view-btn.select-style.btn-style",
      "anime_link": "a[href]",
      "anime_card": "div.wave-block"
    },
    "last_success": "2026-02-19T07:11:18.781397"
  },
  "episode_list": {
    "count": 2915,
    "rules": {
      "player_button": "button.share-button",
      "anime_link": "a[href]"
    },
    "last_success": "2026-02-19T10:03:26.659188"
  },
  "anime_list": {
    "count": 121,
    "rules": {
      "player_button": "button.btn-style.show-more-filter",
      "anime_link": "a[href]"
    },
    "last_success": "2026-02-19T10:34:02.105101"
  }
}