{
  "stream": {
    "count": 293,
    "rules": {
      "player_button": "button.episodes-view-btn.btn-style",
      "anime_link": "a[href]",
      "anime_card": "div.wave-block"
    },
    "last_success": "2026-04-08T19:36:58.905109"
  },
  "episode_list": {
    "count": 7044,
    "rules": {
      "player_button": "button.share-button",
      "anime_link": "a[href]"
    },
    "last_success": "2026-04-08T22:08:39.259928"
  },
  "anime_list": {
    "count": 293,
    "rules": {
      "player_button": "button.btn-style.show-more-filter",
      "anime_link": "a[href]"
    },
    "last_success": "2026-04-08T22:24:31.102370"
  }
}