{
  "stream": {
    "count": 194,
    "rules": {
      "player_button": "button.episodes-view-btn.select-style.btn-style",
      "anime_link": "a[href]",
      "anime_card": "div.wave-block"
    },
    "last_success": "2026-03-12T02:48:47.660817"
  },
  "episode_list": {
    "count": 4667,
    "rules": {
      "player_button": "button.share-button",
      "anime_link": "a[href]"
    },
    "last_success": "2026-03-12T05:46:22.868358"
  },
  "anime_list": {
    "count": 194,
    "rules": {
      "player_button": "button.btn-style.show-more-filter",
      "anime_link": "a[href]"
    },
    "last_success": "2026-03-12T06:13:57.145640"
  }
}