{
  "stream": {
    "count": 373,
    "rules": {
      "player_button": "button.episodes-view-btn.select-style.btn-style",
      "anime_link": "a[href]",
      "anime_card": "div.wave-block"
    },
    "last_success": "2026-05-01T04:06:22.094603"
  },
  "episode_list": {
    "count": 8963,
    "rules": {
      "player_button": "button.share-button",
      "anime_link": "a[href]"
    },
    "last_success": "2026-05-01T06:02:10.170830"
  },
  "anime_list": {
    "count": 373,
    "rules": {
      "player_button": "button.btn-style.show-more-filter",
      "anime_link": "a[href]"
    },
    "last_success": "2026-05-01T06:14:44.307436"
  }
}