{
  "stream": {
    "count": 644,
    "rules": {
      "player_button": "button.episodes-view-btn.select-style.btn-style",
      "anime_link": "a[href]",
      "anime_card": "div.wave-block"
    },
    "last_success": "2026-07-17T08:22:11.789945"
  },
  "episode_list": {
    "count": 15614,
    "rules": {
      "player_button": "button.share-button",
      "anime_link": "a[href]"
    },
    "last_success": "2026-07-17T10:19:48.966402"
  },
  "anime_list": {
    "count": 644,
    "rules": {
      "player_button": "button.btn-style.show-more-filter",
      "anime_link": "a[href]"
    },
    "last_success": "2026-07-17T10:32:20.155567"
  }
}