{
  "stream": {
    "count": 571,
    "rules": {
      "player_button": "button.episodes-view-btn.select-style.btn-style",
      "anime_link": "a[href]",
      "anime_card": "div.wave-block"
    },
    "last_success": "2026-06-26T04:23:16.116732"
  },
  "episode_list": {
    "count": 13732,
    "rules": {
      "player_button": "button.share-button",
      "anime_link": "a[href]"
    },
    "last_success": "2026-06-26T07:34:34.188285"
  },
  "anime_list": {
    "count": 571,
    "rules": {
      "player_button": "button.btn-style.show-more-filter",
      "anime_link": "a[href]"
    },
    "last_success": "2026-06-26T07:53:35.611230"
  }
}